{
    "App_no":"hi_app21",
    "App_name": "आपको अगले साल क्या सरप्राइज मिलने वाला है?"
,
    "Result": [
              "आपके  जीवन  में  एक  सुन्दर सी लड़की  का  आगमन  होगा ",
              "आपको अपनी  DREAM COMPANY से  जॉब  कॉल  आएगा ",
              "आपके नाम का 1 करोड़ का चैक आएगा ",
              "आपको  आपके बचपन की दोस्त PROPOSE करेगी ",
              "आपको कार गिफ्ट में मिलेगी",
              "आपको एक साथ 5 लड़किया PROPOSE करेंगे ",
              ],
    "Result_share":"Satish, 2018 से आपके अच्छे दिन आने वाले है। आपको लोगो का बेशुमार प्यार और बहुत सारे SUPRISES भी मिलेंगे। आपका सरप्राइज बहुत होने होगा और शायद आप बिकुल दंग रह जाएँ। आपने सरप्राइज को सभी के साथ साझा करें और दुसरो को भी उनका सरप्राइज जानने का मौका दें।",

    "App_link":"http://quizonix.com/hi/app/aapko-agle-saal-kya-surprise-milne-vala-hai",
}
